pytest_breed_adapter.py
pytest_breed_adapter-1.2.0.dist-info/METADATA
pytest_breed_adapter-1.2.0.dist-info/RECORD
pytest_breed_adapter-1.2.0.dist-info/WHEEL
pytest_breed_adapter-1.2.0.dist-info/entry_points.txt
pytest_breed_adapter-1.2.0.dist-info/top_level.txt
