Metadata-Version: 2.1
Name: pytest-breed-adapter
Version: 1.2.0
Summary: A simple plugin to connect with breed-server
Home-page: https://github.com/megachweng/pytest-breed-adapter
Author: megachweng
Author-email: megachweng@gmail.com
Maintainer: megachweng
Maintainer-email: megachweng@gmail.com
License: BSD-3
Platform: UNKNOWN
Classifier: Development Status :: 4 - Beta
Classifier: Framework :: Pytest
Classifier: Intended Audience :: Developers
Classifier: Topic :: Software Development :: Testing
Classifier: Programming Language :: Python
Classifier: Programming Language :: Python :: 3.5
Classifier: Programming Language :: Python :: 3.6
Classifier: Programming Language :: Python :: Implementation :: CPython
Classifier: Programming Language :: Python :: Implementation :: PyPy
Classifier: Operating System :: OS Independent
Classifier: License :: OSI Approved :: BSD License
Requires-Python: >=3.5
Requires-Dist: pytest (>=3.5.0)
Requires-Dist: pytest-metadata
